Metadata-Version: 1.1
Name: dopaminekit
Version: 0.9.3
Summary: A library to use DopamineLabs machine learning API
Home-page: https://github.com/DopamineLabs/DopamineKit-Python-Client
Author: Akash Desai
Author-email: kash@usedopamine.com
License: MIT
Download-URL: https://github.com/DopamineLabs/DopamineKit-Python-Client/tarball/0.9.3
Keywords: machinelearning analytics dopamine reinforcement behavior
Platform: UNKNOWN
